api.py
capoomailapi-0.1.0.dist-info/licenses/LICENSE
capoomailapi-0.1.0.dist-info/METADATA
capoomailapi-0.1.0.dist-info/WHEEL
capoomailapi-0.1.0.dist-info/top_level.txt
capoomailapi-0.1.0.dist-info/RECORD
