Metadata-Version: 2.4
Name: capoomailapi
Version: 0.1.0
Summary: Shrine-grade Capoomail API for Firebase Realtime Database
Author: Zeke
License: MIT
License-File: LICENSE
Requires-Dist: firebase-admin
Dynamic: license-file
